surmise/_version.py
surmise/emulation.py
surmise/__init__.py
surmise/test.py
surmise/helper.py
surmise/utilities.py
surmise/calibration.py
surmise/emulationmethods/nuclear-ROSE.py
surmise/emulationmethods/PCGP.py
surmise/emulationmethods/PCGPwImpute.py
surmise/emulationmethods/__init__.py
surmise/emulationmethods/PCGPwM.py
surmise/emulationmethods/PCGPR.py
surmise/emulationmethods/indGP.py
surmise/emulationmethods/PCSK.py
surmise/calibrationmethods/simulationpost.py
surmise/calibrationmethods/__init__.py
surmise/calibrationmethods/directbayes.py
surmise/calibrationmethods/mlbayeswoodbury.py
surmise/calibrationmethods/directbayeswoodbury.py
surmise/utilitiesmethods/metropolis_hastings.py
surmise/utilitiesmethods/LMC.py
surmise/utilitiesmethods/PTLMC.py
surmise/utilitiesmethods/__init__.py
surmise/tests/test_emu_init.py
surmise/tests/test_cal_directbayes.py
surmise/tests/test_new_cal.py
surmise/tests/test_cal_directbayeswoodbury.py
surmise/tests/test_emu_pcgpwimpute.py
surmise/tests/test_emu_predict.py
surmise/tests/test_emu_supplement.py
surmise/tests/test_emu_saveload.py
surmise/tests/test_emu_x1d.py
surmise/tests/test_new_emu_prediction.py
surmise/tests/__init__.py
surmise/tests/test_emu_passfunc.py
surmise/tests/test_emu_update.py
surmise/tests/test_cal_samplers.py
surmise/tests/test_cal_saveload.py
surmise/tests/test_new_emu.py
surmise/tests/test_emu_remove.py
surmise/tests/test_emu_pcgpwm.py
surmise/tests/test_emu_param_str.py
surmise/emulationsupport/matern_covmat.c
surmise/emulationsupport/__init__.py
surmise/emulationsupport/matern_covmat.cpython-310-darwin.so
surmise/emulationsupport/matern_covmat.pyx
surmise-0.4.0.dist-info/RECORD
surmise-0.4.0.dist-info/WHEEL
surmise-0.4.0.dist-info/top_level.txt
surmise-0.4.0.dist-info/METADATA
surmise-0.4.0.dist-info/licenses/LICENSE
