Metadata-Version: 2.4
Name: surmise
Version: 0.4.0
Summary: A modular interface for surrogate models and tools
Home-page: https://github.com/bandframework/surmise
Author: Matthew Plumlee, Özge Sürer, Stefan M. Wild, and Moses Y.-H. Chan
Author-email: moses.chan@northwestern.edu
Maintainer: Moses Y.-H. Chan
Maintainer-email: moses.chan@northwestern.edu
License: MIT
Project-URL: Source, https://github.com/bandframework/surmise
Project-URL: Documentation, https://surmise.readthedocs.io
Project-URL: Tracker, https://github.com/bandframework/surmise/issues
Keywords: surmise
Classifier: Programming Language :: Python :: 3
Classifier: License :: OSI Approved :: MIT License
Classifier: Operating System :: OS Independent
Requires-Python: >=3.9
License-File: LICENSE
Requires-Dist: numpy<2.2.0,>=1.22.0
Requires-Dist: scipy<1.15.0,>=1.9.0
Requires-Dist: scikit-learn>=1.2.0
Requires-Dist: dill>=0.3.8
Requires-Dist: pytest
Dynamic: author
Dynamic: author-email
Dynamic: classifier
Dynamic: description
Dynamic: description-content-type
Dynamic: home-page
Dynamic: keywords
Dynamic: license
Dynamic: license-file
Dynamic: maintainer
Dynamic: maintainer-email
Dynamic: project-url
Dynamic: requires-dist
Dynamic: requires-python
Dynamic: summary
